{
    "id": 88615162,
    "name": "Study",
    "author": "JodyCondor",
    "creators": ["JodyCondor"],
    "verifier": "Jodycondor",
    "verification": "https://youtu.be/J_PzQexiygk?si=lOynQDTzlhb0PxC_",
    "percentToQualify": "100",
    "password": "",
    "records": [

        {
            "user": "Equallake",
            "link": "",
            "percent": 100,
            "hz": 69
       },
     
        {
            "user": "Togatta",
            "link": "",
            "percent": 100,
            "hz": 69
       }
        
    ]
}
